Workbook

Sheet Simulação
B1: Parâmetros
B3: Individual | E3: Pool
B4: Condomínios | C4: 46 | E4: Condomínios | F4: 217
B5: Unidades | C5: 1768 | E5: Unidades | F5: 6445
B6: Custo boletagem | C6: 1 | E6: Custo boletagem | F6: 1
B7: Faturamento | C7: =23000000/3/(C5+F5)*C5 -> 1650391.7 | E7: Faturamento | F7: =23000000/3/(C5+F5)*F5 -> 6016275
B8: Pagamentos | C8: =24000000/3/(C5+F5)*C5 -> 1722147.8 | E8: Pagamentos | F8: =24000000/3/(C5+F5)*F5 -> 6277852.2
B9: Tarifa | C9: 14 | E9: Tarifa | F9: 0

Sheet Resultado
B2: GANHOS AUXILIADORA PREDIAL
G5: Mensal | J5: Trimestral | M5: Anual
D6: Individual | E6: Pool | G6: Individual | H6: Pool | J6: Individual | K6: Pool | M6: Individual | N6: Pool
B7: Boletagem
C8: Preço atribuído | D8: 1.7 | E8: 1.7 | G8: =(D8-Simulação!C6)*Simulação!C5 -> 1237.6 | H8: =(E8-Simulação!F6)*Simulação!F5 -> 4511.5 | J8: =G8*3 -> 3712.8 | K8: =H8*3 -> 13534.5 | M8: =J8*4 -> 14851.2 | N8: =K8*4 -> 54138
C9: Emissão (Distribuição de resultado) | H9: =Resultados!B4*Resultados!G4*Resultados!M4 -> 547.40565 | K9: =H9*3 -> 1642.2169 | N9: =K9*4 -> 6568.8678
B11: Depósito à vista
C12: Saldo médio (Distribuição de resultado) | D12: 0.0913 | E12: 0.0913 | F12: do faturamento | G12: 0 | H12: =Resultados!B4*Resultados!G2*Resultados!M2 -> 3932.8443 | J12: =G12*3 -> 0 | K12: =H12*3 -> 11798.533 | M12: =J12*4 -> 0 | N12: =K12*4 -> 47194.132
B14: Investimento
C15: Saldo médio (Distribuição de resultado) | D15: 0.096 | E15: 0.096 | F15: x o faturamento | G15: 0 | H15: =Resultados!B4*Resultados!G3*Resultados!M3 -> 741.08642 | J15: =G15*3 -> 0 | K15: =H15*3 -> 2223.2593 | M15: =J15*4 -> 0 | N15: =K15*4 -> 8893.0371
B17: Pagamentos
C18: Boletos | D18: 3750 | G18: 0 | H18: =D18*0.2 -> 750 | J18: =G18*3 -> 0 | K18: =H18*3 -> 2250 | M18: =J18*4 -> 0 | N18: =K18*4 -> 9000
B20: Tarifa
C21: Preço | D21: 50 | E21: 0 | G21: =(D21-Simulação!C9)*Simulação!C4 -> 1656 | H21: =(E21-Simulação!F9)*Simulação!F4 -> 0 | J21: =G21*3 -> 4968 | K21: =H21*3 -> 0 | M21: =J21*4 -> 19872 | N21: =K21*4 -> 0
B24: TOTAL | G24: =SUM(G8:G21) -> 2893.6 | H24: =SUM(H8:H21) -> 10482.836 | J24: =SUM(J8:J21) -> 8680.8 | K24: =SUM(K8:K21) -> 31448.509 | M24: =SUM(M8:M21) -> 34723.2 | N24: =SUM(N8:N21) -> 125794.04
G25: =SUM(G24:H24) -> 13376.436 | J25: =SUM(J24:K24) -> 40129.309 | M25: =SUM(M24:N24) -> 160517.24

Sheet Resultados
B1: Distribuição | C1: Resultado | F1: Rateio | G1: % | J1: Conta | K1: Valor | L1: Predial | M1: %
A2: 2024 | B2: 2751739.5 | C2: 11370764 | F2: Depósito à vista | G2: 0.4 | J2: Depósito à vista | K2: 1.0255925e+08 | L2: =Simulação!F7*Resultado!D12 -> 549285.91 | M2: =L2/SUM(K2:L2) -> 0.0053272595
A3: 2025 | B3: 1326211.7 | C3: 22876889 | F3: Investimentos | G3: 0.25 | J3: Investimento | K3: 3.5901688e+08 | L3: =Simulação!F7*Resultado!D15 -> 577562.4 | M3: =L3/SUM(K3:L3) -> 0.0016061494
A4: 2026 | B4: =SUM(B2:B3)/SUM(C2:C3)*C4 -> 1845622.6 | C4: 15500000 | F4: Cobrança | G4: 0.2 | J4: Cobrança | K4: 4339523.3 | L4: =Simulação!F6*Simulação!F5 -> 6445 | M4: =L4/SUM(K4:L4) -> 0.0014829837
